apns2/__init__.py
apns2/client.py
apns2/credentials.py
apns2/errors.py
apns2/payload.py
apns2_plus-0.7.2.1.dist-info/LICENSE
apns2_plus-0.7.2.1.dist-info/METADATA
apns2_plus-0.7.2.1.dist-info/WHEEL
apns2_plus-0.7.2.1.dist-info/RECORD
