Metadata-Version: 2.1
Name: apns2-plus
Version: 0.7.2.1
Summary: A python library for interacting with the Apple Push Notification Service via HTTP/2 protocol
License: MIT
Author: Sergey Petrov
Author-email: me@pr0ger.prg
Requires-Python: >=3.7
Classifier: Development Status :: 4 - Beta
Classifier: License :: OSI Approved :: MIT License
Classifier: Programming Language :: Python :: 3
Classifier: Programming Language :: Python :: 3.7
Classifier: Programming Language :: Python :: 3.8
Classifier: Programming Language :: Python :: 3.9
Classifier: Programming Language :: Python :: 3.10
Classifier: Programming Language :: Python :: 3.11
Classifier: Programming Language :: Python :: 3.12
Classifier: Topic :: Software Development :: Libraries
Requires-Dist: cryptography (>=1.7.2)
Requires-Dist: hyper (>=0.7)
Requires-Dist: pyjwt (>=2.0.0)
